epf/__init__.py
epf/crawler.py
epf/ctx.py
epf/downloader.py
epf/parser.py
epf-1.0.4.dist-info/DESCRIPTION.rst
epf-1.0.4.dist-info/METADATA
epf-1.0.4.dist-info/RECORD
epf-1.0.4.dist-info/WHEEL
epf-1.0.4.dist-info/metadata.json
epf-1.0.4.dist-info/top_level.txt
