Metadata-Version: 2.0
Name: epf
Version: 1.0.4
Summary: Apple EPF crawler, downloader and parser
Home-page: https://github.com/andreif/epf
Author: Andrei Fokau
Author-email: andrei@5monkeys.se
License: MIT
Download-URL: https://github.com/andreif/epf/tarball/1.0.4
Platform: UNKNOWN
Requires-Dist: requests
